magic_module_skaffolder/__init__.py
magic_module_skaffolder/__main__.py
magic_module_skaffolder/api_descriptions.py
magic_module_skaffolder/magic_module.py
magic_module_skaffolder/skaffolder.py
magic_module_skaffolder/yaml.py
magic_module_skaffolder-0.0.3.dist-info/METADATA
magic_module_skaffolder-0.0.3.dist-info/WHEEL
magic_module_skaffolder-0.0.3.dist-info/entry_points.txt
magic_module_skaffolder-0.0.3.dist-info/top_level.txt
magic_module_skaffolder-0.0.3.dist-info/zip-safe
magic_module_skaffolder-0.0.3.dist-info/RECORD
