Metadata-Version: 2.1
Name: magic-module-skaffolder
Version: 0.0.3
Summary: generate and update Magic Module resource definitions
Home-page: https://github.com/binxio/magic-module-skaffolder
Author: Mark van Holsteijn
Author-email: mark.vanholsteijn@xebia.com
Classifier: Environment :: Console
Classifier: License :: OSI Approved :: Apache Software License
Classifier: Development Status :: 3 - Alpha
Classifier: Intended Audience :: Developers
Classifier: Operating System :: POSIX
Classifier: Operating System :: MacOS
Classifier: Operating System :: Unix
Classifier: Programming Language :: Python :: 3
Requires-Dist: requests
Requires-Dist: ruamel-yaml
Requires-Dist: click
Requires-Dist: pattern
Requires-Dist: nltk
